google_search_mcp/__init__.py
google_search_mcp/__main__.py
google_search_mcp-0.1.1.dist-info/METADATA
google_search_mcp-0.1.1.dist-info/WHEEL
google_search_mcp-0.1.1.dist-info/entry_points.txt
google_search_mcp-0.1.1.dist-info/licenses/LICENSE
google_search_mcp-0.1.1.dist-info/RECORD
